py_pushover_simple/__init__.py
py_pushover_simple/pushover.py
py_pushover_simple-0.5.0.dist-info/LICENSE
py_pushover_simple-0.5.0.dist-info/METADATA
py_pushover_simple-0.5.0.dist-info/WHEEL
py_pushover_simple-0.5.0.dist-info/top_level.txt
py_pushover_simple-0.5.0.dist-info/RECORD
