Metadata-Version: 2.1
Name: py-pushover-simple
Version: 0.5.0
Summary: A wrapper for sending push notifications with Pushover
Home-page: https://github.com/prplecake/py_pushover_simple
Author: Matthew Jorgensen
Author-email: matthew@jrgnsn.net
License: UNKNOWN
Project-URL: Documentation, https://github.com/prplecake/py_pushover_simple/wiki
Project-URL: Code, https://github.com/prplecake/py_pushover_simple
Project-URL: Issue Tracker, https://github.com/prplecake/py_pushover_simple/issues
Platform: UNKNOWN
Classifier: Development Status :: 3 - Alpha
Classifier: Environment :: Plugins
Classifier: License :: OSI Approved :: MIT License
Classifier: Operating System :: OS Independent
Classifier: Programming Language :: Python :: 3
Classifier: Programming Language :: Python :: 3.4
Classifier: Programming Language :: Python :: 3.5
Classifier: Programming Language :: Python :: 3.6
Classifier: Programming Language :: Python :: 3.7
Classifier: Natural Language :: English
Classifier: Topic :: Communications
Classifier: Topic :: Utilities
License-File: LICENSE
